main.py
awsx/__init__.py
awsx/switcher.py
awsx-2.1.1.dist-info/LICENSE
awsx-2.1.1.dist-info/METADATA
awsx-2.1.1.dist-info/WHEEL
awsx-2.1.1.dist-info/entry_points.txt
awsx-2.1.1.dist-info/top_level.txt
awsx-2.1.1.dist-info/RECORD
