Metadata-Version: 2.1
Name: awsx
Version: 2.1.1
Summary: awsx
Author-email: Xu <deep.work.max@gmail.com>
Project-URL: Homepage, https://github.com/Xu-Hardy/awsx
Project-URL: Bug Tracker, https://github.com/Xu-Hardy/awsx/issues
Classifier: Programming Language :: Python :: 3
Classifier: License :: OSI Approved :: MIT License
Classifier: Operating System :: OS Independent
Requires-Python: >=3.7
License-File: LICENSE
Requires-Dist: Click
Requires-Dist: boto3
Requires-Dist: configparser
Requires-Dist: pyperclip
Requires-Dist: psutil
